MANIFEST.in
Makefile
README.rst
requirements-test.txt
requirements.txt
setup.cfg
setup.py
scripts/jimmy
src/slippinj/__init__.py
src/slippinj/di.py
src/slippinj.egg-info/PKG-INFO
src/slippinj.egg-info/SOURCES.txt
src/slippinj.egg-info/dependency_links.txt
src/slippinj.egg-info/requires.txt
src/slippinj.egg-info/top_level.txt
src/slippinj/cli/__init__.py
src/slippinj/cli/deploy_configuration.py
src/slippinj/cli/ssh.py
src/slippinj/cli/workflow_configuration.py
src/slippinj/cli/interactive/__init__.py
src/slippinj/cli/interactive/cluster_id.py
src/slippinj/cli/interactive/configuration_file.py
src/slippinj/cli/interactive/properties_file.py
src/slippinj/cli/objects/__init__.py
src/slippinj/cli/objects/wf_configuration_object.py
src/slippinj/cli/scripts/__init__.py
src/slippinj/cli/scripts/anabasii.py
src/slippinj/cli/scripts/basic_script.py
src/slippinj/cli/scripts/cooper.py
src/slippinj/cli/scripts/hersir.py
src/slippinj/cli/scripts/scribe.py
src/slippinj/cli/scripts/tlacuilo.py
src/slippinj/cli/scripts/valet.py
src/slippinj/cli/scripts/tables_configuration/__init__.py
src/slippinj/cli/scripts/tables_configuration/tables_configuration.py
src/slippinj/databases/__init__.py
src/slippinj/databases/db_factory.py
src/slippinj/databases/drivers/__init__.py
src/slippinj/databases/drivers/mysql.py
src/slippinj/databases/drivers/oracle.py
src/slippinj/databases/drivers/postgresql.py
src/slippinj/databases/drivers/sqlserver.py
src/slippinj/emr/__init__.py
src/slippinj/emr/cluster.py
src/slippinj/emr/deploy.py
src/slippinj/emr/job_flow/__init__.py
src/slippinj/emr/job_flow/configuration.py
src/slippinj/emr/job_flow/run.py
src/slippinj/emr/job_flow/arguments/__init__.py
src/slippinj/emr/job_flow/arguments/applications.py
src/slippinj/emr/job_flow/arguments/configurations.py
src/slippinj/emr/job_flow/arguments/instances.py
src/slippinj/emr/job_flow/arguments/steps.py
src/slippinj/emr/job_flow/arguments/tags.py
src/slippinj/filesystem/__init__.py
src/slippinj/filesystem/excel_writer.py
src/slippinj/filesystem/filesystem.py
src/slippinj/filesystem/hdfs.py
src/slippinj/filesystem/yaml_configuration.py
src/slippinj/generator/__init__.py
