Metadata-Version: 1.1
Name: slippinj
Version: 3.0.1
Summary: Tools to generate and deploy Apache Oozie workflows
Home-page: https://github.com/scm-spain/slippin-jimmy
Author: Data Architects SCM Spain
Author-email: data.architecture@scmspain.com
License: GPLv2
Keywords: oozie workflows code generation emr aws
Platform: UNKNOWN
Classifier: Topic :: Software Development :: Build Tools
Classifier: Topic :: Software Development :: Code Generators
Classifier: Programming Language :: Python :: 2
Classifier: Programming Language :: Python :: 2.6
Classifier: Programming Language :: Python :: 2.7
Classifier: License :: OSI Approved :: GNU General Public License v2 (GPLv2)
Classifier: Intended Audience :: Developers
Classifier: Environment :: Console
